veleslibrary/__init__.py
veleslibrary/questionnaires/__init__.py
veleslibrary/questionnaires/pl/__init__.py
veleslibrary/questionnaires/pl/questionnaires.py
veleslibrary/questionnaires/questionnaires.py
veleslibrary/tests/__init__.py
veleslibrary/tests/pl/__init__.py
veleslibrary/tests/pl/tests.py
veleslibrary/tests/tests.py
veleslibrary-0.1.2.dist-info/METADATA
veleslibrary-0.1.2.dist-info/WHEEL
veleslibrary-0.1.2.dist-info/RECORD
